Pytorch1XZiranyuyanChuliShiyongZhinanChuyi/README.md
Pytorch1XZiranyuyanChuliShiyongZhinanChuyi/__init__.py
Pytorch1XZiranyuyanChuliShiyongZhinanChuyi/__main__.py
Pytorch1XZiranyuyanChuliShiyongZhinanChuyi/file.epub
Pytorch1XZiranyuyanChuliShiyongZhinanChuyi/index.html
Pytorch1XZiranyuyanChuliShiyongZhinanChuyi/css/__init__.py
Pytorch1XZiranyuyanChuliShiyongZhinanChuyi/css/annotations.css
Pytorch1XZiranyuyanChuliShiyongZhinanChuyi/css/main.css
Pytorch1XZiranyuyanChuliShiyongZhinanChuyi/css/normalize.css
Pytorch1XZiranyuyanChuliShiyongZhinanChuyi/css/popup.css
Pytorch1XZiranyuyanChuliShiyongZhinanChuyi/font/__init__.py
Pytorch1XZiranyuyanChuliShiyongZhinanChuyi/font/fontello.eot
Pytorch1XZiranyuyanChuliShiyongZhinanChuyi/font/fontello.svg
Pytorch1XZiranyuyanChuliShiyongZhinanChuyi/font/fontello.ttf
Pytorch1XZiranyuyanChuliShiyongZhinanChuyi/font/fontello.woff
Pytorch1XZiranyuyanChuliShiyongZhinanChuyi/img/__init__.py
Pytorch1XZiranyuyanChuliShiyongZhinanChuyi/img/annotator-glyph-sprite.png
Pytorch1XZiranyuyanChuliShiyongZhinanChuyi/img/annotator-icon-sprite.png
Pytorch1XZiranyuyanChuliShiyongZhinanChuyi/img/apple-touch-icon.png
Pytorch1XZiranyuyanChuliShiyongZhinanChuyi/img/cancelfullscreen.png
Pytorch1XZiranyuyanChuliShiyongZhinanChuyi/img/close.png
Pytorch1XZiranyuyanChuliShiyongZhinanChuyi/img/fullscreen.png
Pytorch1XZiranyuyanChuliShiyongZhinanChuyi/img/loader.gif
Pytorch1XZiranyuyanChuliShiyongZhinanChuyi/img/menu-icon.png
Pytorch1XZiranyuyanChuliShiyongZhinanChuyi/img/save.png
Pytorch1XZiranyuyanChuliShiyongZhinanChuyi/img/saved.png
Pytorch1XZiranyuyanChuliShiyongZhinanChuyi/img/settings-s.png
Pytorch1XZiranyuyanChuliShiyongZhinanChuyi/img/settings.png
Pytorch1XZiranyuyanChuliShiyongZhinanChuyi/img/star.png
Pytorch1XZiranyuyanChuliShiyongZhinanChuyi/js/__init__.py
Pytorch1XZiranyuyanChuliShiyongZhinanChuyi/js/epub.js
Pytorch1XZiranyuyanChuliShiyongZhinanChuyi/js/epub.min.js
Pytorch1XZiranyuyanChuliShiyongZhinanChuyi/js/epub.min.map
pytorch_1_x_ziranyuyan_chuli_shiyong_zhinan_chuyi-2024.3.6.0.dist-info/METADATA
pytorch_1_x_ziranyuyan_chuli_shiyong_zhinan_chuyi-2024.3.6.0.dist-info/WHEEL
pytorch_1_x_ziranyuyan_chuli_shiyong_zhinan_chuyi-2024.3.6.0.dist-info/entry_points.txt
pytorch_1_x_ziranyuyan_chuli_shiyong_zhinan_chuyi-2024.3.6.0.dist-info/top_level.txt
pytorch_1_x_ziranyuyan_chuli_shiyong_zhinan_chuyi-2024.3.6.0.dist-info/RECORD
